Metadata-Version: 1.1
Name: pyassemble
Version: 1.0.0
Summary: Assemble project code with all dependencies for offline installation
Home-page: http://github.com/chaokunyang/py_assembly
Author: chaokunyang
Author-email: UNKNOWN
License: Apache License 2.0
Keywords: assembly dist offline install dependencies
Platform: UNKNOWN
Classifier: Programming Language :: Python :: 3.6
Classifier: Intended Audience :: Developers
